[
    {"name": "Mark_Init", "tag": 3, "time": 0, "heap": 2048},
    {"name": "Def_Alloc", "tag": 2, "handle": "RTOS::Registers::task_pool", "bytes": 6},
    {"name": "Def_Alloc", "tag": 2, "handle": "RTOS::Registers::task_pool", "bytes": 1920},
    {"name": "Def_Task", "tag": 0, "handle": "task_sample", "instance": 0},
    {"name": "Debug_Message", "tag": 20, "message": "0\n"},
    {"name": "Mark_Start", "tag": 5, "time": 0, "instance": 0},
    {"name": "Debug_Message", "tag": 20, "message": "u_x: 0 u_y: 0\n"},
    {"name": "Debug_Message", "tag": 20, "message": "m_x: 0 m_y: 0\n"},
    {"name": "Mark_Stop", "tag": 6, "time": 1, "instance": 0},
    {"name": "Mark_Idle", "tag": 8, "time": 2},
    {"name": "Mark_Wake", "tag": 9, "time": 500},
    {"name": "Mark_Start", "tag": 5, "time": 500, "instance": 0},
    {"name": "Debug_Message", "tag": 20, "message": "u_x: 0 u_y: 5\n"},
    {"name": "Debug_Message", "tag": 20, "message": "m_x: 0 m_y: 0\n"},
    {"name": "Mark_Stop", "tag": 6, "time": 502, "instance": 0},
    {"name": "Mark_Idle", "tag": 8, "time": 503},
    {"name": "Mark_Wake", "tag": 9, "time": 1000},
    {"name": "Mark_Start", "tag": 5, "time": 1000, "instance": 0},
    {"name": "Debug_Message", "tag": 20, "message": "u_x: 0 u_y: 10\n"},
    {"name": "Debug_Message", "tag": 20, "message": "m_x: 0 m_y: 4\n"},
    {"name": "Mark_Stop", "tag": 6, "time": 1002, "instance": 0},
    {"name": "Mark_Idle", "tag": 8, "time": 1003},
    {"name": "Mark_Wake", "tag": 9, "time": 1500},
    {"name": "Mark_Start", "tag": 5, "time": 1500, "instance": 0},
    {"name": "Debug_Message", "tag": 20, "message": "u_x: 0 u_y: 15\n"},
    {"name": "Debug_Message", "tag": 20, "message": "m_x: 0 m_y: 9\n"},
    {"name": "Mark_Stop", "tag": 6, "time": 1502, "instance": 0},
    {"name": "Mark_Idle", "tag": 8, "time": 1503},
    {"name": "Mark_Wake", "tag": 9, "time": 2000},
    {"name": "Mark_Start", "tag": 5, "time": 2000, "instance": 0},
    {"name": "Debug_Message", "tag": 20, "message": "u_x: 0 u_y: 19\n"},
    {"name": "Debug_Message", "tag": 20, "message": "m_x: 0 m_y: 13\n"},
    {"name": "Mark_Stop", "tag": 6, "time": 2002, "instance": 0},
    {"name": "Mark_Idle", "tag": 8, "time": 2004},
    {"name": "Mark_Wake", "tag": 9, "time": 2500},
    {"name": "Mark_Start", "tag": 5, "time": 2500, "instance": 0},
    {"name": "Debug_Message", "tag": 20, "message": "u_x: 0 u_y: 23\n"},
    {"name": "Debug_Message", "tag": 20, "message": "m_x: 0 m_y: 17\n"},
    {"name": "Mark_Stop", "tag": 6, "time": 2502, "instance": 0},
    {"name": "Mark_Idle", "tag": 8, "time": 2504},
    {"name": "Mark_Wake", "tag": 9, "time": 3000},
    {"name": "Mark_Start", "tag": 5, "time": 3000, "instance": 0},
    {"name": "Debug_Message", "tag": 20, "message": "u_x: 0 u_y: 26\n"},
    {"name": "Debug_Message", "tag": 20, "message": "m_x: 0 m_y: 20\n"},
    {"name": "Mark_Stop", "tag": 6, "time": 3002, "instance": 0},
    {"name": "Mark_Idle", "tag": 8, "time": 3004},
    {"name": "Mark_Wake", "tag": 9, "time": 3500},
    {"name": "Mark_Start", "tag": 5, "time": 3500, "instance": 0},
    {"name": "Debug_Message", "tag": 20, "message": "u_x: 0 u_y: 29\n"},
    {"name": "Debug_Message", "tag": 20, "message": "m_x: 0 m_y: 23\n"},
    {"name": "Mark_Stop", "tag": 6, "time": 3502, "instance": 0},
    {"name": "Mark_Idle", "tag": 8, "time": 3504},
    {"name": "Mark_Wake", "tag": 9, "time": 4000},
    {"name": "Mark_Start", "tag": 5, "time": 4000, "instance": 0},
    {"name": "Debug_Message", "tag": 20, "message": "u_x: 0 u_y: 32\n"},
    {"name": "Debug_Message", "tag": 20, "message": "m_x: 0 m_y: 26\n"},
    {"name": "Mark_Stop", "tag": 6, "time": 4002, "instance": 0},
    {"name": "Mark_Idle", "tag": 8, "time": 4004},
    {"name": "Mark_Wake", "tag": 9, "time": 4500},
    {"name": "Mark_Start", "tag": 5, "time": 4500, "instance": 0},
    {"name": "Debug_Message", "tag": 20, "message": "u_x: 0 u_y: 35\n"},
    {"name": "Debug_Message", "tag": 20, "message": "m_x: 0 m_y: 29\n"},
    {"name": "Mark_Stop", "tag": 6, "time": 4502, "instance": 0},
    {"name": "Mark_Idle", "tag": 8, "time": 4504},
    {"name": "Mark_Wake", "tag": 9, "time": 5000},
    {"name": "Mark_Start", "tag": 5, "time": 5000, "instance": 0},
    {"name": "Debug_Message", "tag": 20, "message": "u_x: 0 u_y: 37\n"},
    {"name": "Debug_Message", "tag": 20, "message": "m_x: 0 m_y: 31\n"},
    {"name": "Mark_Stop", "tag": 6, "time": 5002, "instance": 0},
    {"name": "Mark_Idle", "tag": 8, "time": 5004},
    {"name": "Mark_Wake", "tag": 9, "time": 5500},
    {"name": "Mark_Start", "tag": 5, "time": 5500, "instance": 0},
    {"name": "Debug_Message", "tag": 20, "message": "u_x: 0 u_y: 39\n"},
    {"name": "Debug_Message", "tag": 20, "message": "m_x: 0 m_y: 33\n"},
    {"name": "Mark_Stop", "tag": 6, "time": 5502, "instance": 0},
    {"name": "Mark_Idle", "tag": 8, "time": 5504},
    {"name": "Mark_Wake", "tag": 9, "time": 6000},
    {"name": "Mark_Start", "tag": 5, "time": 6000, "instance": 0},
    {"name": "Debug_Message", "tag": 20, "message": "u_x: 0 u_y: 41\n"},
    {"name": "Debug_Message", "tag": 20, "message": "m_x: 0 m_y: 35\n"},
    {"name": "Mark_Stop", "tag": 6, "time": 6002, "instance": 0},
    {"name": "Mark_Idle", "tag": 8, "time": 6004},
    {"name": "Mark_Wake", "tag": 9, "time": 6500},
    {"name": "Mark_Start", "tag": 5, "time": 6500, "instance": 0},
    {"name": "Debug_Message", "tag": 20, "message": "u_x: 0 u_y: 42\n"},
    {"name": "Debug_Message", "tag": 20, "message": "m_x: 0 m_y: 36\n"},
    {"name": "Mark_Stop", "tag": 6, "time": 6502, "instance": 0},
    {"name": "Mark_Idle", "tag": 8, "time": 6504},
    {"name": "Mark_Wake", "tag": 9, "time": 7000},
    {"name": "Mark_Start", "tag": 5, "time": 7000, "instance": 0},
    {"name": "Debug_Message", "tag": 20, "message": "u_x: 0 u_y: 44\n"},
    {"name": "Debug_Message", "tag": 20, "message": "m_x: 0 m_y: 38\n"},
    {"name": "Mark_Stop", "tag": 6, "time": 7002, "instance": 0},
    {"name": "Mark_Idle", "tag": 8, "time": 7004},
    {"name": "Mark_Wake", "tag": 9, "time": 7500},
    {"name": "Mark_Start", "tag": 5, "time": 7500, "instance": 0},
    {"name": "Debug_Message", "tag": 20, "message": "u_x: 0 u_y: 45\n"},
    {"name": "Debug_Message", "tag": 20, "message": "m_x: 0 m_y: 39\n"},
    {"name": "Mark_Stop", "tag": 6, "time": 7502, "instance": 0},
    {"name": "Mark_Idle", "tag": 8, "time": 7504},
    {"name": "Mark_Wake", "tag": 9, "time": 8000},
    {"name": "Mark_Start", "tag": 5, "time": 8000, "instance": 0},
    {"name": "Debug_Message", "tag": 20, "message": "u_x: 0 u_y: 46\n"},
    {"name": "Debug_Message", "tag": 20, "message": "m_x: 0 m_y: 39\n"},
    {"name": "Mark_Stop", "tag": 6, "time": 8002, "instance": 0},
    {"name": "Mark_Idle", "tag": 8, "time": 8004},
    {"name": "Mark_Wake", "tag": 9, "time": 8500},
    {"name": "Mark_Start", "tag": 5, "time": 8500, "instance": 0},
    {"name": "Debug_Message", "tag": 20, "message": "u_x: 0 u_y: 47\n"},
    {"name": "Debug_Message", "tag": 20, "message": "m_x: 0 m_y: 39\n"},
    {"name": "Mark_Stop", "tag": 6, "time": 8502, "instance": 0},
    {"name": "Mark_Idle", "tag": 8, "time": 8504},
    {"name": "Mark_Wake", "tag": 9, "time": 9000},
    {"name": "Mark_Start", "tag": 5, "time": 9000, "instance": 0},
    {"name": "Debug_Message", "tag": 20, "message": "u_x: 0 u_y: 48\n"},
    {"name": "Debug_Message", "tag": 20, "message": "m_x: 0 m_y: 39\n"},
    {"name": "Mark_Stop", "tag": 6, "time": 9002, "instance": 0},
    {"name": "Mark_Idle", "tag": 8, "time": 9004},
    {"name": "Mark_Wake", "tag": 9, "time": 9500},
    {"name": "Mark_Start", "tag": 5, "time": 9500, "instance": 0},
    {"name": "Debug_Message", "tag": 20, "message": "u_x: 0 u_y: 49\n"},
    {"name": "Debug_Message", "tag": 20, "message": "m_x: 0 m_y: 39\n"},
    {"name": "Mark_Stop", "tag": 6, "time": 9502, "instance": 0},
    {"name": "Mark_Idle", "tag": 8, "time": 9504},
    {"name": "Mark_Wake", "tag": 9, "time": 10000},
    {"name": "Mark_Start", "tag": 5, "time": 10000, "instance": 0},
    {"name": "Debug_Message", "tag": 20, "message": "u_x: 0 u_y: 50\n"},
    {"name": "Debug_Message", "tag": 20, "message": "m_x: 0 m_y: 39\n"},
    {"name": "Mark_Stop", "tag": 6, "time": 10002, "instance": 0},
    {"name": "Mark_Idle", "tag": 8, "time": 10004},
    {"name": "Mark_Wake", "tag": 9, "time": 10500},
    {"name": "Mark_Start", "tag": 5, "time": 10500, "instance": 0},
    {"name": "Debug_Message", "tag": 20, "message": "u_x: 0 u_y: 51\n"},
    {"name": "Debug_Message", "tag": 20, "message": "m_x: 0 m_y: 39\n"},
    {"name": "Mark_Stop", "tag": 6, "time": 10502, "instance": 0},
    {"name": "Mark_Idle", "tag": 8, "time": 10504},
    {"name": "Mark_Wake", "tag": 9, "time": 11000},
    {"name": "Mark_Start", "tag": 5, "time": 11000, "instance": 0},
    {"name": "Debug_Message", "tag": 20, "message": "u_x: 0 u_y: 51\n"},
    {"name": "Debug_Message", "tag": 20, "message": "m_x: 0 m_y: 39\n"},
    {"name": "Mark_Stop", "tag": 6, "time": 11002, "instance": 0},
    {"name": "Mark_Idle", "tag": 8, "time": 11004},
    {"name": "Mark_Wake", "tag": 9, "time": 11500},
    {"name": "Mark_Start", "tag": 5, "time": 11500, "instance": 0},
    {"name": "Debug_Message", "tag": 20, "message": "u_x: 0 u_y: 51\n"},
    {"name": "Debug_Message", "tag": 20, "message": "m_x: 0 m_y: 39\n"},
    {"name": "Mark_Stop", "tag": 6, "time": 11502, "instance": 0},
    {"name": "Mark_Idle", "tag": 8, "time": 11504},
    {"name": "Mark_Wake", "tag": 9, "time": 12000},
    {"name": "Mark_Start", "tag": 5, "time": 12000, "instance": 0},
    {"name": "Debug_Message", "tag": 20, "message": "u_x: 0 u_y: 51\n"},
    {"name": "Debug_Message", "tag": 20, "message": "m_x: 0 m_y: 39\n"},
    {"name": "Mark_Stop", "tag": 6, "time": 12002, "instance": 0},
    {"name": "Mark_Idle", "tag": 8, "time": 12004},
    {"name": "Mark_Wake", "tag": 9, "time": 12500},
    {"name": "Mark_Start", "tag": 5, "time": 12500, "instance": 0},
    {"name": "Debug_Message", "tag": 20, "message": "u_x: 0 u_y: 51\n"},
    {"name": "Debug_Message", "tag": 20, "message": "m_x: 0 m_y: 39\n"},
    {"name": "Mark_Stop", "tag": 6, "time": 12502, "instance": 0},
    {"name": "Mark_Idle", "tag": 8, "time": 12504},
    {"name": "Mark_Wake", "tag": 9, "time": 13000},
    {"name": "Mark_Start", "tag": 5, "time": 13000, "instance": 0},
    {"name": "Debug_Message", "tag": 20, "message": "u_x: 0 u_y: 51\n"},
    {"name": "Debug_Message", "tag": 20, "message": "m_x: 0 m_y: 39\n"},
    {"name": "Mark_Stop", "tag": 6, "time": 13002, "instance": 0},
    {"name": "Mark_Idle", "tag": 8, "time": 13004},
    {"name": "Mark_Wake", "tag": 9, "time": 13500},
    {"name": "Mark_Start", "tag": 5, "time": 13500, "instance": 0},
    {"name": "Debug_Message", "tag": 20, "message": "u_x: 0 u_y: 51\n"},
    {"name": "Debug_Message", "tag": 20, "message": "m_x: 0 m_y: 39\n"},
    {"name": "Mark_Stop", "tag": 6, "time": 13502, "instance": 0},
    {"name": "Mark_Idle", "tag": 8, "time": 13504},
    {"name": "Mark_Wake", "tag": 9, "time": 14000},
    {"name": "Mark_Start", "tag": 5, "time": 14000, "instance": 0},
    {"name": "Debug_Message", "tag": 20, "message": "u_x: 0 u_y: 51\n"},
    {"name": "Debug_Message", "tag": 20, "message": "m_x: 0 m_y: 39\n"},
    {"name": "Mark_Stop", "tag": 6, "time": 14002, "instance": 0},
    {"name": "Mark_Idle", "tag": 8, "time": 14004},
    {"name": "Mark_Wake", "tag": 9, "time": 14500},
    {"name": "Mark_Start", "tag": 5, "time": 14500, "instance": 0},
    {"name": "Debug_Message", "tag": 20, "message": "u_x: 0 u_y: 51\n"},
    {"name": "Debug_Message", "tag": 20, "message": "m_x: 0 m_y: 39\n"},
    {"name": "Mark_Stop", "tag": 6, "time": 14502, "instance": 0},
    {"name": "Mark_Idle", "tag": 8, "time": 14504},
    {"name": "Mark_Wake", "tag": 9, "time": 15000},
    {"name": "Mark_Start", "tag": 5, "time": 15000, "instance": 0},
    {"name": "Debug_Message", "tag": 20, "message": "u_x: 0 u_y: 51\n"},
    {"name": "Debug_Message", "tag": 20, "message": "m_x: 0 m_y: 39\n"},
    {"name": "Mark_Stop", "tag": 6, "time": 15002, "instance": 0},
    {"name": "Mark_Idle", "tag": 8, "time": 15004},
    {"name": "Mark_Wake", "tag": 9, "time": 15500},
    {"name": "Mark_Start", "tag": 5, "time": 15500, "instance": 0},
    {"name": "Debug_Message", "tag": 20, "message": "u_x: 0 u_y: 51\n"},
    {"name": "Debug_Message", "tag": 20, "message": "m_x: 0 m_y: 39\n"},
    {"name": "Mark_Stop", "tag": 6, "time": 15502, "instance": 0},
    {"name": "Mark_Idle", "tag": 8, "time": 15504},
    {"name": "Mark_Wake", "tag": 9, "time": 16000},
    {"name": "Mark_Start", "tag": 5, "time": 16000, "instance": 0},
    {"name": "Debug_Message", "tag": 20, "message": "u_x: 0 u_y: 51\n"},
    {"name": "Debug_Message", "tag": 20, "message": "m_x: 0 m_y: 39\n"},
    {"name": "Mark_Stop", "tag": 6, "time": 16002, "instance": 0},
    {"name": "Mark_Idle", "tag": 8, "time": 16004},
    {"name": "Mark_Wake", "tag": 9, "time": 16500},
    {"name": "Mark_Start", "tag": 5, "time": 16500, "instance": 0},
    {"name": "Debug_Message", "tag": 20, "message": "u_x: 0 u_y: 51\n"},
    {"name": "Debug_Message", "tag": 20, "message": "m_x: 0 m_y: 39\n"},
    {"name": "Mark_Stop", "tag": 6, "time": 16502, "instance": 0},
    {"name": "Mark_Idle", "tag": 8, "time": 16504},
    {"name": "Mark_Wake", "tag": 9, "time": 17000},
    {"name": "Mark_Start", "tag": 5, "time": 17000, "instance": 0},
    {"name": "Debug_Message", "tag": 20, "message": "u_x: 0 u_y: 51\n"},
    {"name": "Debug_Message", "tag": 20, "message": "m_x: 0 m_y: 39\n"},
    {"name": "Mark_Stop", "tag": 6, "time": 17002, "instance": 0},
    {"name": "Mark_Idle", "tag": 8, "time": 17004},
    {"name": "Mark_Wake", "tag": 9, "time": 17500},
    {"name": "Mark_Start", "tag": 5, "time": 17500, "instance": 0},
    {"name": "Debug_Message", "tag": 20, "message": "u_x: 0 u_y: 51\n"},
    {"name": "Debug_Message", "tag": 20, "message": "m_x: 0 m_y: 39\n"},
    {"name": "Mark_Stop", "tag": 6, "time": 17502, "instance": 0},
    {"name": "Mark_Idle", "tag": 8, "time": 17504},
    {"name": "Mark_Wake", "tag": 9, "time": 18000},
    {"name": "Mark_Start", "tag": 5, "time": 18000, "instance": 0},
    {"name": "Debug_Message", "tag": 20, "message": "u_x: 0 u_y: 51\n"},
    {"name": "Debug_Message", "tag": 20, "message": "m_x: 0 m_y: 39\n"},
    {"name": "Mark_Stop", "tag": 6, "time": 18002, "instance": 0},
    {"name": "Mark_Idle", "tag": 8, "time": 18004},
    {"name": "Mark_Wake", "tag": 9, "time": 18500},
    {"name": "Mark_Start", "tag": 5, "time": 18500, "instance": 0},
    {"name": "Debug_Message", "tag": 20, "message": "u_x: 0 u_y: 51\n"},
    {"name": "Debug_Message", "tag": 20, "message": "m_x: 0 m_y: 39\n"},
    {"name": "Mark_Stop", "tag": 6, "time": 18502, "instance": 0},
    {"name": "Mark_Idle", "tag": 8, "time": 18504},
    {"name": "Mark_Wake", "tag": 9, "time": 19000},
    {"name": "Mark_Start", "tag": 5, "time": 19000, "instance": 0},
    {"name": "Debug_Message", "tag": 20, "message": "u_x: 0 u_y: 51\n"},
    {"name": "Debug_Message", "tag": 20, "message": "m_x: 0 m_y: 39\n"},
    {"name": "Mark_Stop", "tag": 6, "time": 19002, "instance": 0},
    {"name": "Mark_Idle", "tag": 8, "time": 19004},
    {"name": "Mark_Wake", "tag": 9, "time": 19500},
    {"name": "Mark_Start", "tag": 5, "time": 19500, "instance": 0},
    {"name": "Debug_Message", "tag": 20, "message": "u_x: 0 u_y: 51\n"},
    {"name": "Debug_Message", "tag": 20, "message": "m_x: 0 m_y: 39\n"},
    {"name": "Mark_Stop", "tag": 6, "time": 19502, "instance": 0},
    {"name": "Mark_Idle", "tag": 8, "time": 19504},
    {"name": "Mark_Wake", "tag": 9, "time": 20000},
    {"name": "Mark_Start", "tag": 5, "time": 20000, "instance": 0},
    {"name": "Debug_Message", "tag": 20, "message": "u_x: 0 u_y: 51\n"},
    {"name": "Debug_Message", "tag": 20, "message": "m_x: 0 m_y: 39\n"},
    {"name": "Mark_Stop", "tag": 6, "time": 20002, "instance": 0},
    {"name": "Mark_Idle", "tag": 8, "time": 20004},
    {"name": "Mark_Wake", "tag": 9, "time": 20500},
    {"name": "Mark_Start", "tag": 5, "time": 20500, "instance": 0},
    {"name": "Debug_Message", "tag": 20, "message": "u_x: 0 u_y: 51\n"},
    {"name": "Debug_Message", "tag": 20, "message": "m_x: 0 m_y: 39\n"},
    {"name": "Mark_Stop", "tag": 6, "time": 20502, "instance": 0},
    {"name": "Mark_Idle", "tag": 8, "time": 20504},
    {"name": "Mark_Wake", "tag": 9, "time": 21000}
]
